chgksuite_qt/__main__.py
chgksuite_qt/gui.py
chgksuite_qt/version.py
chgksuite_qt-0.0.2.dist-info/LICENSE.txt
chgksuite_qt-0.0.2.dist-info/METADATA
chgksuite_qt-0.0.2.dist-info/WHEEL
chgksuite_qt-0.0.2.dist-info/entry_points.txt
chgksuite_qt-0.0.2.dist-info/top_level.txt
chgksuite_qt-0.0.2.dist-info/RECORD
