Metadata-Version: 2.1
Name: chgksuite_qt
Version: 0.0.2
Summary: A GUI wrapper for chgksuite using PyQt6
Home-page: https://gitlab.com/peczony/chgksuite_qt
Author: Alexander Pecheny
Author-email: ap@pecheny.me
Classifier: Programming Language :: Python :: 3
Classifier: License :: OSI Approved :: MIT License
Classifier: Operating System :: OS Independent
License-File: LICENSE.txt
Requires-Dist: chgksuite
Requires-Dist: PyQt6
